{
  "Pacientes": [
    {
      "id": 1,
      "nombre": "",
      "apellido1": "",
      "apellido2": "",
      "cedula": "",
      "telefono1": "",
      "telefono2": "",
      "direccion1": "",
      "direccion2": "",
      "fecha_nacimiento": "",
      "patologias": "",
      "tratamientos": ""
    }
  ],
  "Reservaciones": [
    {
      "id": 2,
      "Paciente": "carlos",
      "FechaIngreso": "2023-03-24T22:01:42.501Z",
      "Procedimientos": "Biopsia",
      "FechaSalida": "2023-04-05T22:01:42.501Z"
    },
    {
      "id": 1681581551447,
      "Paciente": "11111111",
      "FechaIngreso": "2023-04-15",
      "Procedimientos": "Ecografia",
      "FechaSalida": "0001-01-01T00:00:00"
    },
    {
      "id": 1681622629469,
      "Paciente": "1111",
      "FechaIngreso": "2023-04-15",
      "Procedimientos": "Biopsia Ecografia ",
      "FechaSalida": "1111"
    }
  ],
  "Historial": [
    {
      "id": 1,
      "Procedimientos": "Biopsia",
      "FechaProcedimiento": "2023-04-15",
      "Tratamientos": "curita"
    },
    {
      "id": 2,
      "Procedimientos": "Ecografia",
      "FechaProcedimiento": "2023-04-15",
      "Tratamientos": "curita"
    }
  ]
}